logging_process/__init__.py
logging_process/clog.py
logging_process/exampl2.py
logging_process/example.py
logging_process-0.9.6.dist-info/LICENSE
logging_process-0.9.6.dist-info/METADATA
logging_process-0.9.6.dist-info/WHEEL
logging_process-0.9.6.dist-info/top_level.txt
logging_process-0.9.6.dist-info/RECORD
