Metadata-Version: 2.1
Name: logging-process
Version: 0.9.6
Summary: 多进程日志，继承自python官方logging，解决多进程下log日志丢失及混乱问题,增加配置示例2,以时间分割日志文件时，可自定义文件名拼接方式
Home-page: https://github.com/AsiaZhang123/process_log
Author: zyz
Author-email: 329737612@qq.com
License: UNKNOWN
Download-URL: https://github.com/AsiaZhang123/process_log/issues
Platform: UNKNOWN
Classifier: Programming Language :: Python
Classifier: License :: OSI Approved :: MIT License
Classifier: Operating System :: OS Independent
Requires-Dist: portalocker (>=2.3.0)
